paddle/__init__.py
paddle/crm.py
paddle/cubed_sphere_ui.py
paddle/cubed_sphere_utils.py
paddle/evolve_kinetics.py
paddle/example_save.py
paddle/find_init_params.py
paddle/nc2pt.py
paddle/plot_cubed_sphere_panel.py
paddle/pt2nc.py
paddle/setup_profile.py
paddle/write_profile.py
paddle-1.2.3.dist-info/METADATA
paddle-1.2.3.dist-info/WHEEL
paddle-1.2.3.dist-info/entry_points.txt
paddle-1.2.3.dist-info/licenses/LICENSE
paddle-1.2.3.dist-info/RECORD
