Metadata-Version: 2.4
Name: paddle
Version: 1.2.3
Summary: Python Atmospheric Dynamics: Discovery and Learning about Exoplanets. An open-source, user-friendly python frontend of canoe
Project-URL: Homepage, https://github.com/elijah-mullens/paddle
Project-URL: Repository, https://github.com/elijah-mullens/paddle
Project-URL: Issues, https://github.com/elijah-mullens/paddle/issues
Author-email: Elijah Mullens <eem85@cornell.edu>, Cheng Li <chengcli@umich.edu>
License-File: LICENSE
Classifier: Development Status :: 3 - Alpha
Classifier: Intended Audience :: Developers
Classifier: Intended Audience :: Science/Research
Classifier: Programming Language :: Python
Classifier: Programming Language :: Python :: 3
Classifier: Programming Language :: Python :: 3 :: Only
Classifier: Programming Language :: Python :: 3.9
Classifier: Programming Language :: Python :: 3.10
Classifier: Programming Language :: Python :: 3.11
Classifier: Programming Language :: Python :: 3.12
Classifier: Programming Language :: Python :: 3.13
Classifier: Topic :: Scientific/Engineering :: Astronomy
Classifier: Topic :: Scientific/Engineering :: Atmospheric Science
Classifier: Topic :: Scientific/Engineering :: Physics
Requires-Python: >=3.9
Requires-Dist: scipy
Requires-Dist: snapy>=1.1.5
Requires-Dist: torch<=2.7.1,>=2.7.0
Provides-Extra: dev
Requires-Dist: pytest>=7; extra == 'dev'
